{"cameraMode":{"drawMode":0,"name":"Shaded","section":"Shading Mode"},"sceneLighting":true,"audioPlay":false,"sceneViewState":{"showFog":true,"showMaterialUpdate":true,"showSkybox":true,"showFlares":true,"showImageEffects":true,"showParticleSystems":true,"showVisualEffectGraphs":true,"m_FxEnabled":true},"in2DMode":false,"pivot":{"x":204.1906280517578,"y":7.033768653869629,"z":10.215770721435547},"rotation":{"x":0.20392851531505586,"y":0.33319002389907839,"z":-0.07407888025045395,"w":0.9175906181335449},"size":92.3368911743164,"orthographic":false}